odoo/addons/shopinvader_search_engine_product_template_multi_link/README.rst
odoo/addons/shopinvader_search_engine_product_template_multi_link/__init__.py
odoo/addons/shopinvader_search_engine_product_template_multi_link/__manifest__.py
odoo/addons/shopinvader_search_engine_product_template_multi_link/i18n/shopinvader_product_template_multi_link.pot
odoo/addons/shopinvader_search_engine_product_template_multi_link/i18n/shopinvader_search_engine_product_template_multi_link.pot
odoo/addons/shopinvader_search_engine_product_template_multi_link/models/__init__.py
odoo/addons/shopinvader_search_engine_product_template_multi_link/models/product_product.py
odoo/addons/shopinvader_search_engine_product_template_multi_link/readme/CONTRIBUTORS.rst
odoo/addons/shopinvader_search_engine_product_template_multi_link/readme/CREDITS.rst
odoo/addons/shopinvader_search_engine_product_template_multi_link/readme/DESCRIPTION.rst
odoo/addons/shopinvader_search_engine_product_template_multi_link/schemas/__init__.py
odoo/addons/shopinvader_search_engine_product_template_multi_link/schemas/product_link.py
odoo/addons/shopinvader_search_engine_product_template_multi_link/schemas/product_product.py
odoo/addons/shopinvader_search_engine_product_template_multi_link/static/description/index.html
odoo/addons/shopinvader_search_engine_product_template_multi_link/tests/__init__.py
odoo/addons/shopinvader_search_engine_product_template_multi_link/tests/common.py
odoo/addons/shopinvader_search_engine_product_template_multi_link/tests/test_product.py
odoo_addon_shopinvader_search_engine_product_template_multi_link-16.0.1.0.0.2.dist-info/METADATA
odoo_addon_shopinvader_search_engine_product_template_multi_link-16.0.1.0.0.2.dist-info/WHEEL
odoo_addon_shopinvader_search_engine_product_template_multi_link-16.0.1.0.0.2.dist-info/top_level.txt
odoo_addon_shopinvader_search_engine_product_template_multi_link-16.0.1.0.0.2.dist-info/RECORD
